fastcli/__init__.py
fastcli/__main__.py
fastcli/fastcli.py
fastcli-0.2.0.dist-info/AUTHORS.md
fastcli-0.2.0.dist-info/LICENSE
fastcli-0.2.0.dist-info/METADATA
fastcli-0.2.0.dist-info/WHEEL
fastcli-0.2.0.dist-info/top_level.txt
fastcli-0.2.0.dist-info/RECORD
